{
  "tags": [
    {
      "name": "#tag",
      "id": "3bc09950-e5d7-11ec-9a36-db88dcdc9193"
    },
    {
      "name": "#delete",
      "id": "7a821ec0-e5d7-11ec-9a36-db88dcdc9193"
    },
    {
      "name": "#edit",
      "id": "8b8325c0-e5d7-11ec-9a36-db88dcdc9193"
    },
    {
      "name": "#note",
      "id": "c89ca080-e5d7-11ec-9a36-db88dcdc9193"
    }
  ],
  "notes": [
    {
      "title": "First note",
      "content": "Here you can create any #tag and it will appear in the field on left side of your screen",
      "id": "df429ed0-e5d6-11ec-8d76-b336e0217b6b",
      "tags": [
        {
          "name": "#tag",
          "id": "3bc09950-e5d7-11ec-9a36-db88dcdc9193"
        }
      ]
    },
    {
      "title": "Second note",
      "content": "You can press button #delete for removing #note from list",
      "id": "ec9d3310-e5d6-11ec-8d76-b336e0217b6b",
      "tags": [
        {
          "name": "#delete",
          "id": "7a821ec0-e5d7-11ec-9a36-db88dcdc9193"
        },
        {
          "name": "#note",
          "id": "c89ca080-e5d7-11ec-9a36-db88dcdc9193"
        }
      ]
    },
    {
      "title": "Third note",
      "content": "You can press button #edit for updating #note",
      "id": "f0d58590-e5d6-11ec-8d76-b336e0217b6b",
      "tags": [
        {
          "name": "#edit",
          "id": "8b8325c0-e5d7-11ec-9a36-db88dcdc9193"
        },
        {
          "name": "#note",
          "id": "c89ca080-e5d7-11ec-9a36-db88dcdc9193"
        }
      ]
    },
    {
      "title": "Fourth note",
      "content": "You can select any #tag for filtering notes by it",
      "id": "be619bc0-e5d7-11ec-9a36-db88dcdc9193",
      "tags": [
        {
          "name": "#tag",
          "id": "3bc09950-e5d7-11ec-9a36-db88dcdc9193"
        }
      ]
    }
  ]
}